Metadata-Version: 2.1
Name: lyywxocr
Version: 1.4
Summary: yyjdgui for lyy
Author: lyy
Author-email: 
License: MIT
License-File: LICENSE
